sma_rsi_indicators/__init__.py
sma_rsi_indicators/sma_rsi.py
sma_rsi_indicators-0.1.5.dist-info/LICENSE.txt
sma_rsi_indicators-0.1.5.dist-info/METADATA
sma_rsi_indicators-0.1.5.dist-info/WHEEL
sma_rsi_indicators-0.1.5.dist-info/top_level.txt
sma_rsi_indicators-0.1.5.dist-info/RECORD
